corextext
