Metadata-Version: 1.1
Name: corextext
Version: 0.2.8
Summary: Return components/latent factors that explain the most multivariate mutual information in the data under Linear Gaussian model. For comparison, PCA returns components explaining the most variance in the data.
Home-page: https://github.com/brekelma/corextext
Author: Rob Brekelmans/Greg Ver Steeg
Author-email: brekelma@usc.edu
License: AGPL-3.0
Download-URL: https://github.com/brekelma/corextext
Platform: UNKNOWN
Classifier: Programming Language :: Python
Classifier: Programming Language :: Python :: 3.6
